robot_excel/__init__.py
robot_excel/index.py
robot_excel/utils.py
robot_excel/xlwings_excel.py
robot_excel-0.3.0.dist-info/METADATA
robot_excel-0.3.0.dist-info/WHEEL
robot_excel-0.3.0.dist-info/RECORD
